azerbaijani_stopwords/__init__.py
azerbaijani_stopwords-0.1.0.dist-info/LICENSE
azerbaijani_stopwords-0.1.0.dist-info/METADATA
azerbaijani_stopwords-0.1.0.dist-info/WHEEL
azerbaijani_stopwords-0.1.0.dist-info/top_level.txt
azerbaijani_stopwords-0.1.0.dist-info/RECORD
