Metadata-Version: 2.1
Name: azerbaijani_stopwords
Version: 0.1.0
Summary: A lightweight Python package providing Azerbaijani stopwords for NLP tasks.
Author: Cafarli
License: MIT
Classifier: Programming Language :: Python :: 3
Classifier: License :: OSI Approved :: MIT License
Classifier: Operating System :: OS Independent
Classifier: Topic :: Text Processing :: Linguistic
Requires-Python: >=3.6
License-File: LICENSE
